ankipy/__init__.py
ankipy/app.py
ankipy/defaults.json
ankipy/tools/__init__.py
ankipy/tools/defaults.py
ankipy/tools/guid.py
ankipy-0.1.0.dist-info/WHEEL
ankipy-0.1.0.dist-info/METADATA
ankipy-0.1.0.dist-info/RECORD
