Metadata-Version: 2.1
Name: ankipy
Version: 0.1.0
Summary: Create anki decks and cards from your Python application
Home-page: UNKNOWN
License: MIT
Author: patarapolw
Author-email: patarapolw@gmail.com
Classifier: License :: OSI Approved :: MIT License
Classifier: Programming Language :: Python :: 2
Classifier: Programming Language :: Python :: 2.7
Classifier: Programming Language :: Python :: 3
Classifier: Programming Language :: Python :: 3.4
Classifier: Programming Language :: Python :: 3.5
Classifier: Programming Language :: Python :: 3.6
Classifier: Programming Language :: Python :: 3.7
Requires-Dist: bs4 (>=0.0.1,<0.0.2)
Requires-Dist: importlib_resources (>=1.0,<2.0)
